prevision_quantum_nn/__init__.py
prevision_quantum_nn/applications/__init__.py
prevision_quantum_nn/applications/application.py
prevision_quantum_nn/applications/classification_application.py
prevision_quantum_nn/applications/multiclassification_application.py
prevision_quantum_nn/applications/regression_application.py
prevision_quantum_nn/applications/reinforcement_learning_application.py
prevision_quantum_nn/applications/reinforcement_learning/__init__.py
prevision_quantum_nn/applications/reinforcement_learning/base_learner.py
prevision_quantum_nn/applications/reinforcement_learning/deep_q_learning.py
prevision_quantum_nn/applications/reinforcement_learning/policy.py
prevision_quantum_nn/applications/reinforcement_learning/q_learning.py
prevision_quantum_nn/applications/reinforcement_learning/qnn_q_learning.py
prevision_quantum_nn/dataset/__init__.py
prevision_quantum_nn/dataset/dataset.py
prevision_quantum_nn/models/__init__.py
prevision_quantum_nn/models/qnn.py
prevision_quantum_nn/models/pennylane_backend/__init__.py
prevision_quantum_nn/models/pennylane_backend/qnn_pennylane.py
prevision_quantum_nn/models/pennylane_backend/qnn_pennylane_cv.py
prevision_quantum_nn/models/pennylane_backend/qnn_pennylane_qubit.py
prevision_quantum_nn/models/utilities/__init__.py
prevision_quantum_nn/models/utilities/early_stopper.py
prevision_quantum_nn/models/utilities/losses.py
prevision_quantum_nn/models/utilities/to_categorical.py
prevision_quantum_nn/postprocessing/__init__.py
prevision_quantum_nn/postprocessing/postprocess.py
prevision_quantum_nn/postprocessing/plotter/__init__.py
prevision_quantum_nn/postprocessing/plotter/phase_space_plotter.py
prevision_quantum_nn/postprocessing/plotter/phase_space_plotter_1d.py
prevision_quantum_nn/postprocessing/plotter/phase_space_plotter_2d.py
prevision_quantum_nn/preprocessing/__init__.py
prevision_quantum_nn/preprocessing/feature_engineering.py
prevision_quantum_nn/preprocessing/polynomial_expansion.py
prevision_quantum_nn-1.0.2.dist-info/LICENSE
prevision_quantum_nn-1.0.2.dist-info/METADATA
prevision_quantum_nn-1.0.2.dist-info/WHEEL
prevision_quantum_nn-1.0.2.dist-info/top_level.txt
prevision_quantum_nn-1.0.2.dist-info/RECORD
