Metadata-Version: 2.1
Name: prevision-quantum-nn
Version: 1.0.2
Summary: Prevision Automating Quantum Neural Networks Applications
Home-page: UNKNOWN
Author: prevision.io
Author-email: prevision@prevision.io
License: MIT
Platform: UNKNOWN
Requires-Python: >=3.6.8
Requires-Dist: setuptools
Requires-Dist: numpy
Requires-Dist: tensorflow
Requires-Dist: sympy
Requires-Dist: matplotlib
Requires-Dist: strawberryfields (>=0.15)
Requires-Dist: pennylane
Requires-Dist: pennylane-sf
Requires-Dist: lightgbm
Requires-Dist: openml
Requires-Dist: pandas
Requires-Dist: scikit-learn
Requires-Dist: tqdm
Requires-Dist: gym
Requires-Dist: box2d-py
Requires-Dist: imageio
Requires-Dist: dill
